{
  "id": "0fb119a9-dd0e-4112-8160-db4b58b4e08c",
  "runtime": "bash",
  "purpose": "verify S04 planning code paths and current file tree",
  "script_chars": 662,
  "started_at": "2026-05-17T11:08:46.867Z",
  "finished_at": "2026-05-17T11:08:46.992Z",
  "exit_code": 0,
  "signal": null,
  "timed_out": false,
  "duration_ms": 125,
  "stdout_bytes": 345,
  "stderr_bytes": 0,
  "stdout_truncated": false,
  "stderr_truncated": false,
  "stdout_path": "J:\\cmt-rs\\.gsd\\exec\\0fb119a9-dd0e-4112-8160-db4b58b4e08c.stdout",
  "stderr_path": "J:\\cmt-rs\\.gsd\\exec\\0fb119a9-dd0e-4112-8160-db4b58b4e08c.stderr"
}
