{
  "id": "d40aeb76-6a71-4c7e-971a-9aafa772c4db",
  "runtime": "bash",
  "purpose": "cargo fmt check after domain contract additions",
  "script_chars": 33,
  "started_at": "2026-05-17T08:56:03.748Z",
  "finished_at": "2026-05-17T08:56:04.000Z",
  "exit_code": 1,
  "signal": null,
  "timed_out": false,
  "duration_ms": 252,
  "stdout_bytes": 8184,
  "stderr_bytes": 0,
  "stdout_truncated": false,
  "stderr_truncated": false,
  "stdout_path": "J:\\cmt-rs\\.gsd\\exec\\d40aeb76-6a71-4c7e-971a-9aafa772c4db.stdout",
  "stderr_path": "J:\\cmt-rs\\.gsd\\exec\\d40aeb76-6a71-4c7e-971a-9aafa772c4db.stderr"
}
